SouPyX/__init__.py
SouPyX/core.py
SouPyX/display.py
SouPyX/effects.py
SouPyX/models.py
SouPyX/spatial.py
SouPyX/synths.py
SouPyX/version.py
SouPyX-1.0.6.dist-info/LICENSE
SouPyX-1.0.6.dist-info/METADATA
SouPyX-1.0.6.dist-info/WHEEL
SouPyX-1.0.6.dist-info/top_level.txt
SouPyX-1.0.6.dist-info/RECORD
